ovito/__init__.py
ovito/__init__.pyi
ovito/_scene_class.py
ovito/ipykernel_launcher.py
ovito/py.typed
ovito/qt_compat.py
ovito/_codegen/__init__.py
ovito/_codegen/codegen_scene.py
ovito/_extensions/__init__.py
ovito/_extensions/anari.py
ovito/_extensions/averaging.py
ovito/_extensions/binning.py
ovito/_extensions/bondanalysis.py
ovito/_extensions/correlation.py
ovito/_extensions/crystalanalysis.py
ovito/_extensions/galamost.py
ovito/_extensions/gltf.py
ovito/_extensions/grid.py
ovito/_extensions/lammps.py
ovito/_extensions/mesh.py
ovito/_extensions/meshmod.py
ovito/_extensions/netcdf.py
ovito/_extensions/ospray.py
ovito/_extensions/oxdna.py
ovito/_extensions/particles.py
ovito/_extensions/povray.py
ovito/_extensions/pyscript.py
ovito/_extensions/stdmod.py
ovito/_extensions/stdobj.py
ovito/_extensions/structurefactor.py
ovito/_extensions/tachyon.py
ovito/_extensions/threejs.py
ovito/_extensions/vorotop.py
ovito/_extensions/scripts/__init__.py
ovito/_extensions/scripts/modifiers/Assign shared visual element.py
ovito/_extensions/scripts/modifiers/Calculate local entropy.py
ovito/_extensions/scripts/modifiers/Identify fcc planar faults.py
ovito/_extensions/scripts/modifiers/Render LAMMPS regions.py
ovito/_extensions/scripts/modifiers/Shrink-wrap simulation box.py
ovito/_extensions/scripts/modifiers/__init__.py
ovito/_extensions/scripts/readers/ASE Database.py
ovito/_extensions/scripts/readers/ASE Trajectory.py
ovito/_extensions/scripts/readers/__init__.py
ovito/_extensions/scripts/writers/ASE Trajectory.py
ovito/_extensions/scripts/writers/__init__.py
ovito/data/__init__.py
ovito/data/__init__.pyi
ovito/data/_bonds_class.py
ovito/data/_cutoff_neighbor_finder.py
ovito/data/_data_collection.py
ovito/data/_data_objects_dict.py
ovito/data/_data_table.py
ovito/data/_lines.py
ovito/data/_nearest_neighbor_finder.py
ovito/data/_ovito_ndarray_adapter.py
ovito/data/_particles_class.py
ovito/data/_property_class.py
ovito/data/_property_container.py
ovito-3.14.1.dist-info/licenses/LICENSE.MIT.txt
ovito-3.14.1.dist-info/METADATA
ovito-3.14.1.dist-info/WHEEL
ovito-3.14.1.dist-info/entry_points.txt
ovito-3.14.1.dist-info/top_level.txt
ovito-3.14.1.dist-info/RECORD
