Metadata-Version: 2.4
Name: ovito
Version: 3.14.1
Summary: A scientific data visualization and analysis software for particle-based simulations
Author-email: "OVITO GmbH, Germany" <mail@ovito.org>
License-Expression: MIT
Project-URL: Homepage, https://www.ovito.org
Project-URL: Bug Tracker, https://gitlab.com/stuko/ovito
Project-URL: Documentation, https://docs.ovito.org/python/
Classifier: Programming Language :: Python :: 3
Classifier: Programming Language :: C++
Classifier: Operating System :: Microsoft :: Windows
Classifier: Operating System :: MacOS :: MacOS X
Classifier: Operating System :: POSIX :: Linux
Classifier: Development Status :: 5 - Production/Stable
Classifier: Topic :: Scientific/Engineering :: Chemistry
Classifier: Topic :: Scientific/Engineering :: Physics
Classifier: Topic :: Scientific/Engineering :: Visualization
Requires-Python: >=3.10
License-File: LICENSE.MIT.txt
Requires-Dist: numpy>=1.23
Requires-Dist: traits>=6.3
Requires-Dist: PySide6>=6.8.3
Dynamic: license-file
